{
  "id": "hill_valley/2015/twin_pines_mall",
  "type": "room",
  "definition": "room",
  "name": "Twin Pines Mall",
  "description": "A sprawling, multi-tiered 'Consumer Optimization Hub,' now operating under the moniker 'Twin Pines Retail & Leisure Nexus.' This architectural marvel stands as a monument to the hyper-efficient, data-driven consumerism of the 2010s, a decade retrospectively characterized by algorithmic trend forecasting and precisely segmented market psychology. Within its perpetually climate-controlled interior, a bewildering array of 'experience-shops' offer goods and services meticulously designed to fulfill algorithmically predicted 'needs,' many of which are, to a dispassionate observer, utterly superfluous to the continued functioning of the universal simulation. It's a space where bio-luminescent signage guides individuals, often in algorithmically optimized trajectories, in search of 'unforeseen desires,' only to discover those desires have been pre-fulfilled. The ambient soundscape pulsates with the harmonious hum of synchronized commercial jingles and the subtle, collective sigh of data-rich credit-chips being efficiently processed. It is, of course, also a designated 'Temporal Anomaly Hotspot,' though no active consumer unit ever seems to consciously process this, primarily due to the ongoing 'Temporal Anomaly Appreciation Day' sales on optimized comfort wear.",
  "exits": {
    "north": "hill_valley/2015/mall_parking_n",
    "northeast": "hill_valley/2015/mall_parking_ne",
    "east": "hill_valley/2015/mall_parking_e",
    "southeast": "hill_valley/2015/mall_parking_se",
    "south": "hill_valley/2015/mall_parking_s",
    "southwest": "hill_valley/2015/mall_parking_sw",
    "west": "hill_valley/2015/mall_parking_w",
    "northwest": "hill_valley/2015/mall_parking_nw"
  },
  "tags": [
    "shopping",
    "time_travel_site"
  ]
}